weex_sdk/__init__.py
weex_sdk/auth.py
weex_sdk/client.py
weex_sdk/exceptions.py
weex_sdk/logger.py
weex_sdk/models.py
weex_sdk/websocket.py
weex_sdk/api/__init__.py
weex_sdk/api/account.py
weex_sdk/api/ai.py
weex_sdk/api/market.py
weex_sdk/api/trade.py
weex_sdk/utils/__init__.py
weex_sdk/utils/helpers.py
weex_sdk/utils/validators.py
weex_sdk-1.0.10.dist-info/licenses/LICENSE
weex_sdk-1.0.10.dist-info/METADATA
weex_sdk-1.0.10.dist-info/WHEEL
weex_sdk-1.0.10.dist-info/top_level.txt
weex_sdk-1.0.10.dist-info/RECORD
