Metadata-Version: 2.4
Name: weex-sdk
Version: 1.0.10
Summary: A comprehensive Python SDK for Weex exchange API (HTTP + WebSocket)
Home-page: https://github.com/weex/weex-sdk-python
Author: Weex SDK Contributors
License: Apache-2.0
Classifier: Development Status :: 4 - Beta
Classifier: Intended Audience :: Developers
Classifier: Operating System :: OS Independent
Classifier: Programming Language :: Python :: 3
Classifier: Programming Language :: Python :: 3.8
Classifier: Programming Language :: Python :: 3.9
Classifier: Programming Language :: Python :: 3.10
Classifier: Programming Language :: Python :: 3.11
Classifier: Programming Language :: Python :: 3.12
Classifier: Topic :: Software Development :: Libraries :: Python Modules
Classifier: Topic :: Office/Business :: Financial :: Investment
Requires-Python: >=3.8
License-File: LICENSE
Requires-Dist: requests>=2.31.0
Requires-Dist: aiohttp>=3.9.0
Requires-Dist: websocket-client>=1.6.0
Requires-Dist: websockets>=12.0
Provides-Extra: dev
Requires-Dist: pytest>=7.4.0; extra == "dev"
Requires-Dist: black>=23.0.0; extra == "dev"
Requires-Dist: mypy>=1.5.0; extra == "dev"
Requires-Dist: ruff>=0.1.0; extra == "dev"
Requires-Dist: build>=0.10.0; extra == "dev"
Requires-Dist: twine>=4.0.0; extra == "dev"
Dynamic: home-page
Dynamic: license
Dynamic: license-file
Dynamic: requires-python
